{
  "note": {
    "name": "note",
    "body": [
      "---",
      "title: $F_NAME",
      "path: $REL_PATH",
      "created: $YEAR-$MONTH-$DATE $HOUR:$MINUTE",
      "id: $UUID",
      "---"
    ]
  },

  "meeting": {
    "name": "meet",
    "body": [
      "---",
      "title: $F_NAME",
      "path: $REL_PATH",
      "created: $YEAR-$MONTH-$DATE $HOUR:$MINUTE",
      "id: $UUID",
      "---",
      "",
      "# overview",
      "",
      "### metadata",
      "",
      "- _attendees_: ",
      "  - ",
      "  - ",
      "- _date_: ",
      "- _context_: null",
      "",
      "# prep",
      "",
      "# agenda",
      "",
      "1. [] item_1",
      "2. [] item_2",
      "3. [] item_3",
      "",
      "# notes",
      "",
      "# ais",
      "",
      "- [ ] item_1",
      "- [ ] item_2"
    ]
  },

  "book": {
    "name": "book", 
    "body": [
      "---",
      "title: $F_NAME",
      "path: $REL_PATH",
      "created: $YEAR-$MONTH-$DATE $HOUR:$MINUTE",
      "id: $UUID",
      "---",
      "",
      "# overview",
      "",
      "### metadata",
      "",
      "- _title_: $1",
      "- _author_: ",
      "- _series_: null",
      "- _misc_: null",
      "",
      "### summary",
      "",
      "# experience",
      "",
      "### review",
      "",
      "**stars:** X/10",
      "",
      "### notes/takeaways"
    ]
  },

  "person": {
    "name": "person",
    "body": [
      "---",
      "title: $F_NAME",
      "path: $REL_PATH",
      "created: $YEAR-$MONTH-$DATE $HOUR:$MINUTE",
      "id: $UUID",
      "---",
      "",
      "# about",
      "",
      "### meta",
      "",
      "- full name: $1",
      "- relation: ",
      "- birthday: ",
      "",
      "# life",
      "",
      "# relation",
      "",
      "### recent",
      "",
      "### gift ideas"
    ]
  },

  "word": {
    "name": "word",
    "body": [
      "---",
      "title: $F_NAME",
      "path: $REL_PATH",
      "created: $YEAR-$MONTH-$DATE $HOUR:$MINUTE",
      "id: $UUID",
      "---",
      "",
      "# definition",
      "",
      "_part_of_speech:_ ",
      "",
      "1. ",
      "2. ",
      "",
      "# synonyms",
      "",
      "# usage",
      "",
      "# etymology",
      "",
      "# misc",
      "",
      "# related"
    ]
  },

  "place": {
    "name": "place",
    "body": [
      "---",
      "title: $F_NAME",
      "path: $REL_PATH",
      "created: $YEAR-$MONTH-$DATE $HOUR:$MINUTE",
      "id: $UUID",
      "---",
      "",
      "# overview",
      "",
      "### visits",
      "",
      "- ",
      "",
      "# attractions",
      "",
      "### great",
      "",
      "### good",
      "",
      "### bad",
      "",
      "### recommended to me",
      "",
      "# food",
      "",
      "### great",
      "",
      "### good",
      "",
      "### bad",
      "",
      "### recommended to me",
      "",
      "# accommodations",
      "",
      "### great",
      "",
      "### good",
      "",
      "### bad",
      "",
      "### recommended to me",
      ""
    ]
  },

  "algorithm": {
    "name": "algorithm",
    "body": [
      "---",
      "title: $F_NAME",
      "path: $REL_PATH",
      "created: $YEAR-$MONTH-$DATE $HOUR:$MINUTE",
      "id: $UUID",
      "---",
      "",
      "# overview",
      "",
      "### description",
      "",
      "### complexity",
      "",
      "### applications",
      "",
      "# implementation",
      "",
      "### pseudocode",
      "",
      "### code",
      "",
      "# misc",
      "",
      "### related",
      "",
      "### references",
      ""
    ]
  },

  "competitive_programming_question": {
    "name": "cpq",
    "body": [
      "---",
      "title: $F_NAME",
      "path: $REL_PATH",
      "created: $YEAR-$MONTH-$DATE $HOUR:$MINUTE",
      "id: $UUID",
      "---",
      "",
      "# overview",
      "",
      "_Question:_",
      "_Answer:_",
      "",
      "# tags",
      "",
      "### concepts",
      "",
      "### related questions",
      "",
      "# problem statement",
      "",
      "Via [Leetcode](**URL HERE**):",
      "",
      "> problem statement",
      "",
      "# approach 1: NAME OF APPROACH",
      "",
      "### concept",
      "",
      "### implementation",
      "",
      "#### pseudocode",
      "",
      "#### code",
      "",
      "### performance",
      "",
      "_time complexity:_ ",
      "_space complexity:_",
      "",
      "### key takeaways",
      ""
    ]
  }
}